pymvlapi
