Metadata-Version: 1.1
Name: pymvlapi
Version: 0.0.4
Summary: Module providing programmer-friendly wrapper over MarketingVillas API
Home-page: https://github.com/mbwk/pymvlapi
Author: Red Ape Solutions Sdn Bhd
Author-email: karl@redapesolutions.com
License: UNKNOWN
Download-URL: https://github.com/mbwk/pymvlapi/tarball/0.0.4
Platform: UNKNOWN
Classifier: Development Status :: 3 - Alpha
